{
  "malicous_phone": {
    "p1": { "phone": "02439446395" },
    "p2": { "phone": "02499950060" },
    "p3": { "phone": "02499954266" },
    "p4": { "phone": "0249997041" },
    "p5": { "phone": "02444508888" },
    "p6": { "phone": "02499950412" },
    "p7": { "phone": "0249997037" },
    "p8": { "phone": "02499997044" },
    "p9": { "phone": "02499950212" },
    "p10": { "phone": "02499950036" },
    "p11": { "phone": "0249997038" },
    "p12": { "phone": "0249992623" },
    "p13": { "phone": "0249997035" },
    "p14": { "phone": "0249994266" },
    "p15": { "phone": "02499985212" },
    "p16": { "phone": "0245678520" },
    "p17": { "phone": "02499985220" },
    "p18": { "phone": "0249997044" },

    "p19": { "phone": "19003439" },
    "p20": { "phone": "19004510" },
    "p21": { "phone": "19002191" },
    "p22": { "phone": "19003441" },
    "p23": { "phone": "19002170" },
    "p24": { "phone": "19002446" },
    "p25": { "phone": "19001095" },
    "p26": { "phone": "19002190" },
    "p27": { "phone": "19002196" },
    "p28": { "phone": "19004562" },
    "p29": { "phone": "19003440" },
    "p30": { "phone": "19001199" },

    "p31": { "phone": "02899964439" },
    "p32": { "phone": "02856786501" },
    "p33": { "phone": "02899964438" },
    "p34": { "phone": "02899964437" },
    "p35": { "phone": "02873034653" },
    "p36": { "phone": "02899950012" },
    "p37": { "phone": "02873065555" },
    "p38": { "phone": "02899964448" },
    "p39": { "phone": "02822000266" },
    "p40": { "phone": "0287108690" },
    "p41": { "phone": "02899950015" },
    "p42": { "phone": "02899958588" },
    "p43": { "phone": "02871099082" },
    "p44": { "phone": "02899996142" }
  }
}
